bayesfrag/__init__.py
bayesfrag/gpr.py
bayesfrag/inference.py
bayesfrag/postprocess.py
bayesfrag/sites.py
bayesfrag/spatialcorrelation.py
bayesfrag/utils.py
bayesfrag-0.1.0.dist-info/LICENSE
bayesfrag-0.1.0.dist-info/METADATA
bayesfrag-0.1.0.dist-info/WHEEL
bayesfrag-0.1.0.dist-info/top_level.txt
bayesfrag-0.1.0.dist-info/RECORD
