Metadata-Version: 2.1
Name: bayesfrag
Version: 0.1.0
Summary: Bayesian estimation of empirical seismic fragility functions
Author: Lukas Bodenmann
License: BSD-3-Clause
Project-URL: Repository, https://github.com/bodlukas/BayesFrag
Requires-Python: >=3.10
License-File: LICENSE
Requires-Dist: numpyro >=0.13.2
Requires-Dist: pandas >=1.5.3
Requires-Dist: arviz >=0.15.1
